mednsktest/__init__.py
mednsktest/cli.py
mednsktest/repo/201401_uzd.txt
mednsktest/repo/201402_gyne.txt
mednsktest/repo/201812_uzd.txt
mednsktest-0.2.0.dist-info/DESCRIPTION.rst
mednsktest-0.2.0.dist-info/METADATA
mednsktest-0.2.0.dist-info/RECORD
mednsktest-0.2.0.dist-info/WHEEL
mednsktest-0.2.0.dist-info/entry_points.txt
mednsktest-0.2.0.dist-info/metadata.json
mednsktest-0.2.0.dist-info/top_level.txt
