Metadata-Version: 2.0
Name: mednsktest
Version: 0.2.0
Summary: Тесты с курсов НГМУ. Консольное приложение.
Home-page: https://github.com/idlesign/mednsktest
Author: Igor `idle sign` Starikov
Author-email: idlesign@yandex.ru
License: BSD 3-Clause License
Platform: UNKNOWN
Classifier: Development Status :: 4 - Beta
Classifier: Operating System :: OS Independent
Classifier: Programming Language :: Python
Classifier: Programming Language :: Python :: 2
Classifier: Programming Language :: Python :: 2.7
Classifier: License :: OSI Approved :: BSD License
Provides-Extra: cli
Provides-Extra: cli
Requires-Dist: click (>=2.0); extra == 'cli'
